core/__init__.py
core/ai/__init__.py
core/ai/agent_config.py
core/ai/q_assistant.py
core/ai/prompts/__init__.py
core/ai/prompts/chain_of_thought.py
core/ai/prompts/clin_structure.py
core/ai/prompts/context_fidelity.py
core/ai/prompts/default_system_role.py
core/ai/prompts/evaluation_scoring.py
core/ai/prompts/few_shot.py
core/ai/prompts/gov_compliance.py
core/ai/prompts/library.py
core/ai/prompts/output_constraints.py
core/ai/prompts/partials.py
core/ai/prompts/past_performance.py
core/ai/prompts/red_team_gov.py
core/ai/prompts/reflection.py
core/ai/prompts/registry.py
core/ai/prompts/role_playing.py
core/ai/prompts/solicitation_sections.py
core/ai/prompts/step_back.py
core/ai/prompts/thought_process.py
core/ai/prompts/threat_modeling.py
core/ai/prompts/tool_execution.py
core/auth/__init__.py
core/auth/microsoft_365_provider.py
core/auth/microsoft_sso.py
core/aws/__init__.py
core/aws/secret_loader.py
core/aws/secrets_manager.py
core/code_graph/__init__.py
core/code_graph/builder.py
core/code_graph/cli.py
core/code_graph/models.py
core/code_graph/scanner.py
core/code_graph/tool.py
core/ingest/__init__.py
core/ingest/heading_extraction.py
core/user/__init__.py
core/user/profile.py
core/utils/__init__.py
core/utils/app_config.py
core/utils/logger.py
core/utils/qd_config.py
quantumdrive-1.3.81.dist-info/licenses/LICENSE
webapp/__init__.py
webapp/app.py
webapp/static/css/styles.css
webapp/static/images/favicon.ico
webapp/static/images/qdrive_logo.png
webapp/static/images/qdrive_logo2.png
webapp/static/js/app.js
webapp/templates/analytics.html
webapp/templates/base.html
webapp/templates/dashboard.html
webapp/templates/directory.html
webapp/templates/privacy.html
webapp/templates/reports.html
webapp/templates/system_details.html
webapp/templates/task_execution.html
webapp/templates/terms.html
quantumdrive-1.3.81.dist-info/METADATA
quantumdrive-1.3.81.dist-info/WHEEL
quantumdrive-1.3.81.dist-info/top_level.txt
quantumdrive-1.3.81.dist-info/RECORD
