Metadata-Version: 2.4
Name: quantumdrive
Version: 1.3.81
Summary: QuantumDrive platform and SDK
Author: Chris Steel
Author-email: chris.steel@alphsix.com
License: LicenseRef-AlphSix-Proprietary
Classifier: Programming Language :: Python :: 3.11
Classifier: Programming Language :: Python :: 3.12
Classifier: Programming Language :: Python :: 3.13
Classifier: Operating System :: OS Independent
Requires-Python: >=3.11,<3.14
License-File: LICENSE
Requires-Dist: agentfoundry
Requires-Dist: flask>=3.0.0
Requires-Dist: gunicorn>=21.0.0
Requires-Dist: toml
Requires-Dist: msal>=1.24.0
Requires-Dist: python-dotenv>=1.0.0
Requires-Dist: awscli>=1.44.14
Requires-Dist: boto3
Requires-Dist: botocore>=1.42.24
Requires-Dist: sqlalchemy>=2.0.0
Requires-Dist: posthog>=3.0.0
Requires-Dist: docutils
Requires-Dist: markdown-it-py
Requires-Dist: mdurl
Requires-Dist: packaging
Requires-Dist: urllib3
Dynamic: author
Dynamic: author-email
Dynamic: classifier
Dynamic: description
Dynamic: description-content-type
Dynamic: license
Dynamic: license-file
Dynamic: requires-dist
Dynamic: requires-python
Dynamic: summary
